market_features/__init__.py
market_features/jquery-3.3.1.min.js
market_features/market_features.html.jinja
market_features/style.css
market_features/treeview.js
market_features-0.5.6.dist-info/LICENSE
market_features-0.5.6.dist-info/METADATA
market_features-0.5.6.dist-info/WHEEL
market_features-0.5.6.dist-info/entry_points.txt
market_features-0.5.6.dist-info/top_level.txt
market_features-0.5.6.dist-info/RECORD
