Metadata-Version: 2.1
Name: market-features
Version: 0.5.6
Summary: nosetest plug in to Create IntelliJ Style HTML Test Results Report
Home-page: https://github.com/StefanRatzke/market-features
Author: Stefan Ratzke, Caleb Carvalho, Ralf Thaenert
Author-email: stefan-ratzke@t-online.de
Maintainer: Stefan Ratzke, Caleb Carvalho, Ralf Thaenert
Maintainer-email: caleb.carvalho@gmail.com
License: UNKNOWN
Download-URL: https://github.com/StefanRatzke/market-features/tarball/0.5.2
Platform: UNKNOWN
Classifier: Development Status :: 2 - Pre-Alpha
Classifier: Environment :: Console
Classifier: Intended Audience :: Developers
Classifier: Natural Language :: English
Classifier: License :: OSI Approved :: Apache Software License
Classifier: Operating System :: OS Independent
Classifier: Programming Language :: Python :: 3
Classifier: Programming Language :: Python :: 3.6
Classifier: Topic :: Software Development :: Testing
Requires-Dist: Jinja2 (<3.0,>=2.6)
